segee/__init__.py
segee/exceptions.py
segee/monoids.py
segee/binary_indexed_tree/__init__.py
segee/binary_indexed_tree/backbone/__init__.py
segee/binary_indexed_tree/backbone/generic_binary_indexed_tree.py
segee/binary_indexed_tree/backbone/generic_range_updatable_binary_indexed_tree.py
segee/binary_indexed_tree/specialized/__init__.py
segee/binary_indexed_tree/specialized/binary_indexed_tree.py
segee/binary_indexed_tree/specialized/range_add_binary_indexed_tree.py
segee/segment_tree/__init__.py
segee/segment_tree/backbone/__init__.py
segee/segment_tree/backbone/generic_segment_tree.py
segee/segment_tree/specialized/__init__.py
segee/segment_tree/specialized/max_segment_tree.py
segee/segment_tree/specialized/min_segment_tree.py
segee/segment_tree/specialized/sum_segment_tree.py
segee/shared/backbone/__init__.py
segee/shared/backbone/sequence_protocol.py
segee/shared/protocols/__init__.py
segee/shared/protocols/additive.py
segee/shared/protocols/comparable.py
segee/shared/protocols/multiplicative.py
segee/shared/queries/__init__.py
segee/shared/queries/point_add_query.py
segee/shared/queries/range_add_query.py
segee/shared/queries/range_max_query.py
segee/shared/queries/range_min_query.py
segee/shared/queries/range_sum_query.py
segee/shared/updates/__init__.py
segee/shared/updates/range_update.py
segee_cli/__init__.py
segee_cli/main.py
segee-0.2.0.dist-info/METADATA
segee-0.2.0.dist-info/WHEEL
segee-0.2.0.dist-info/entry_points.txt
segee-0.2.0.dist-info/licenses/LICENSE
segee-0.2.0.dist-info/RECORD
