Metadata-Version: 2.4
Name: segee
Version: 0.2.0
Summary: A high-performance, enterprise-grade Segment Tree implementation for Python
Project-URL: Homepage, https://github.com/nodashin6/segee
Project-URL: Documentation, https://github.com/nodashin6/segee/blob/main/docs/usage.md
Project-URL: Repository, https://github.com/nodashin6/segee.git
Project-URL: Issues, https://github.com/nodashin6/segee/issues
Author-email: nodashin <nodashin.jpn@gmail.com>
Maintainer-email: nodashin <nodashin.jpn@gmail.com>
License: MIT License
License-File: LICENSE
Keywords: algorithms,data-structures,range-query,segment-tree
Classifier: Development Status :: 4 - Beta
Classifier: Intended Audience :: Developers
Classifier: License :: OSI Approved :: MIT License
Classifier: Operating System :: OS Independent
Classifier: Programming Language :: Python :: 3
Classifier: Programming Language :: Python :: 3.12
Classifier: Programming Language :: Python :: 3.13
Classifier: Topic :: Scientific/Engineering
Classifier: Topic :: Software Development :: Libraries :: Python Modules
Classifier: Typing :: Typed
Requires-Python: >=3.12
Provides-Extra: dev
Requires-Dist: mypy>=1.0.0; extra == 'dev'
Requires-Dist: pre-commit>=3.0.0; extra == 'dev'
Requires-Dist: pytest-cov>=4.0.0; extra == 'dev'
Requires-Dist: pytest>=7.0.0; extra == 'dev'
Requires-Dist: ruff>=0.1.0; extra == 'dev'
Provides-Extra: docs
Requires-Dist: sphinx-rtd-theme>=1.2.0; extra == 'docs'
Requires-Dist: sphinx>=5.0.0; extra == 'docs'
Provides-Extra: test
Requires-Dist: pytest-cov>=4.0.0; extra == 'test'
Requires-Dist: pytest>=7.0.0; extra == 'test'
